{"sections":{"main":{"type":"main-product","blocks":{"b7eb1a00-40f5-4188-ae77-55540c26fc8a":{"type":"title","settings":{"heading_tag":"h3"}},"29a38174-111c-4a43-8463-6ba49df8af42":{"type":"shopify:\/\/apps\/judge-me-reviews\/blocks\/preview_badge\/61ccd3b1-a9f2-4160-9fe9-4fec8413e5d8","settings":{}},"ba91d8f6-71b6-4529-86e3-1bb15a3eb1e7":{"type":"price","settings":{"show_taxes_notice":false}},"description":{"type":"description","settings":{"collapse_content":false,"show_below_gallery":false}},"feature_with_icon_WmcH4J":{"type":"feature_with_icon","settings":{"text":"15\/15K Waterproof","link":"","icon":"none","custom_icon":"shopify:\/\/shop_images\/format_color_reset_FILL0_wght400_GRAD0_opsz48.svg","icon_width":16,"background":"#ffffff","text_color":"#fa51a2","border_color":""}},"feature_with_icon_biQ9Dp":{"type":"feature_with_icon","settings":{"text":"C0 PFAS-Freee DWR","link":"","icon":"picto-earth","icon_width":16,"background":"#ffffff","text_color":"#fa51a2","border_color":""}},"feature_with_icon_JREbFy":{"type":"feature_with_icon","settings":{"text":"8 Pockets","link":"","icon":"none","custom_icon":"shopify:\/\/shop_images\/pocket.svg","icon_width":16,"background":"#ffffff","text_color":"#fa51a2","border_color":""}},"feature_with_icon_BgG37f":{"type":"feature_with_icon","settings":{"text":"Insulated with Vents","link":"","icon":"picto-star","icon_width":16,"background":"#ffffff","text_color":"#fa51a2","border_color":""}},"1d7f4d79-e72a-4fb4-8f60-d10b63a65f6a":{"type":"variant_picker","settings":{"hide_sold_out_variants":false,"selector_style":"block","swatch_selector_style":"swatch","variant_image_options":"","size_chart_page":""}},"quantity_selector":{"type":"quantity_selector","settings":{}},"f3ce9d09-1900-4cbd-9e11-5e22fc673142":{"type":"inventory","settings":{"show_in_stock_quantity":true,"low_inventory_threshold":4,"show_progress_bar":false,"progress_bar_max_value":50}},"buy_buttons":{"type":"buy_buttons","settings":{"show_payment_button":true,"show_gift_card_recipient":true,"atc_button_background":"#0ca5a0","atc_button_text_color":"#ffffff","payment_button_background":"rgba(0,0,0,0)","payment_button_text_color":"rgba(0,0,0,0)"}},"share_buttons":{"type":"share_buttons","settings":{}},"ac5f0647-7059-4519-9bec-02ae62112234":{"type":"accordion","settings":{"show_below_gallery":true,"icon":"picto-star","title":"{{ product.metafields.custom.why_you_need_these_pants_title.value }}","content":"{{ product.metafields.custom.why_you_need_these_pants_contents | metafield_tag }}","liquid":"","page":""}},"cab822e7-f6a7-485e-8459-63610b11fead":{"type":"accordion","settings":{"show_below_gallery":true,"icon":"picto-info","title":"{{ product.metafields.custom.feature_title.value }}","content":"{{ product.metafields.custom.features_content | metafield_tag }}","liquid":"","page":""}},"text_hGVhWk":{"type":"text","settings":{"text":"{{ product.metafields.custom.extra_description.value.zali_pant_info | metafield_tag }}"}}},"block_order":["b7eb1a00-40f5-4188-ae77-55540c26fc8a","29a38174-111c-4a43-8463-6ba49df8af42","ba91d8f6-71b6-4529-86e3-1bb15a3eb1e7","description","feature_with_icon_WmcH4J","feature_with_icon_biQ9Dp","feature_with_icon_JREbFy","feature_with_icon_BgG37f","1d7f4d79-e72a-4fb4-8f60-d10b63a65f6a","quantity_selector","f3ce9d09-1900-4cbd-9e11-5e22fc673142","buy_buttons","share_buttons","ac5f0647-7059-4519-9bec-02ae62112234","cab822e7-f6a7-485e-8459-63610b11fead","text_hGVhWk"],"settings":{"color_scheme":"","container_size":"lg","product_info_size":43,"show_sticky_add_to_cart":true,"center_basic_info":true,"desktop_media_layout":"carousel_thumbnails_bottom","desktop_media_grid_gap":30,"mobile_controls":"thumbnails","enable_media_autoplay":true,"enable_video_looping":false,"enable_image_zoom":true,"max_image_zoom_level":3}},"2ce34e20-050d-47d9-878c-e9a21dd77cc1":{"type":"text-with-icons","blocks":{"template--16147330269374__2ce34e20-050d-47d9-878c-e9a21dd77cc1-1684223812e9e222a0-0":{"type":"item","settings":{"icon":"picto-return","icon_width":24,"mobile_icon_width":24,"title":"30 DAY RETURN\/EXCHANGE","content":"<p>Try on at home risk free - we offer 30 day exchages and returns.<\/p>"}},"template--16147330269374__2ce34e20-050d-47d9-878c-e9a21dd77cc1-1684223812e9e222a0-1":{"type":"item","settings":{"icon":"picto-customer-support","icon_width":24,"mobile_icon_width":24,"title":"ONE-ON-ONE CUSTOMER SERVICE","content":"<p>Need help finding the right pants? You can always chat to us!<\/p>"}},"template--16147330269374__2ce34e20-050d-47d9-878c-e9a21dd77cc1-1684223812e9e222a0-2":{"type":"item","settings":{"icon":"picto-delivery-truck","icon_width":24,"mobile_icon_width":24,"title":"SHIPPING WORLDWIDE","content":"<p>We offer click 'n' collect, domestic, and international shipping!<\/p>"}},"101944bf-71c1-40a2-ac3b-2369324904f7":{"type":"item","settings":{"icon":"picto-pin","icon_width":24,"mobile_icon_width":24,"title":"FIND A STOCKIST","content":"<p>Looking to find Nobody's Princess in your local store? Find an Australian or NZ stockist <a href=\"https:\/\/nobodysprincess.com.au\/pages\/stockists?ose=false\" target=\"_blank\" title=\"https:\/\/nobodysprincess.com.au\/pages\/stockists?ose=false\">here<\/a>.<\/p>"}}},"block_order":["template--16147330269374__2ce34e20-050d-47d9-878c-e9a21dd77cc1-1684223812e9e222a0-0","template--16147330269374__2ce34e20-050d-47d9-878c-e9a21dd77cc1-1684223812e9e222a0-1","template--16147330269374__2ce34e20-050d-47d9-878c-e9a21dd77cc1-1684223812e9e222a0-2","101944bf-71c1-40a2-ac3b-2369324904f7"],"settings":{"color_scheme":"","separate_section_with_border":false,"stack_on_mobile":true,"icon_color":"#fa51a2","text_color":"rgba(0,0,0,0)","text_alignment":"center"}},"170901338901ec3060":{"type":"apps","blocks":{"judge_me_reviews_review_widget_PfzhPa":{"type":"shopify:\/\/apps\/judge-me-reviews\/blocks\/review_widget\/61ccd3b1-a9f2-4160-9fe9-4fec8413e5d8","settings":{}}},"block_order":["judge_me_reviews_review_widget_PfzhPa"],"settings":{"color_scheme":"","separate_section_with_border":true,"remove_vertical_spacing":false,"remove_horizontal_spacing":false}},"ee31ce00-e842-4044-b9af-4d7c2a88ae68":{"type":"recently-viewed-products","settings":{"separate_section_with_border":false,"color_scheme":"","hide_product_information":false,"stack_products":false,"products_count":5,"products_per_row_mobile":"2","products_per_row_desktop":6,"horizontal_spacing_factor":1,"vertical_spacing_factor":1,"subheading":"your recently viewed items","title":"STILL THINKING ABOUT THESE?","content":""}}},"order":["main","2ce34e20-050d-47d9-878c-e9a21dd77cc1","170901338901ec3060","ee31ce00-e842-4044-b9af-4d7c2a88ae68"]}